feishu/__init__.py
feishu/client.py
feishu/config.py
feishu/errors.py
feishu/api/__init__.py
feishu/api/approval.py
feishu/api/contact.py
feishu/api/group.py
feishu/api/messages.py
feishu/api/spread_sheet.py
feishu/models/__init__.py
feishu/models/approval.py
feishu/models/group.py
feishu/models/message.py
feishu/models/user.py
auto_feishu-0.0.15.dist-info/LICENSE
auto_feishu-0.0.15.dist-info/METADATA
auto_feishu-0.0.15.dist-info/WHEEL
auto_feishu-0.0.15.dist-info/top_level.txt
auto_feishu-0.0.15.dist-info/RECORD
