Metadata-Version: 2.2
Name: auto-feishu
Version: 0.0.15
Summary: Automation tools for feishu
Author-email: Dragon-GCS <878173121@qq.com>
Classifier: Intended Audience :: Developers
Classifier: License :: OSI Approved :: MIT License
Classifier: Programming Language :: Python :: 3
Classifier: Natural Language :: Chinese (Simplified)
Classifier: Topic :: Office/Business
Classifier: Topic :: Software Development :: Libraries
Classifier: Topic :: Utilities
Requires-Python: >=3.9
License-File: LICENSE
Requires-Dist: httpx
Requires-Dist: pydantic
Requires-Dist: pydantic_settings[toml]
Provides-Extra: dev
Provides-Extra: pandas
Requires-Dist: pandas; extra == "pandas"
